MANIFEST.in
README.rst
setup.py
tfset/__init__.py
tfset/server.py
tfset.egg-info/PKG-INFO
tfset.egg-info/SOURCES.txt
tfset.egg-info/dependency_links.txt
tfset.egg-info/not-zip-safe
tfset.egg-info/requires.txt
tfset.egg-info/top_level.txt
tfset/bin/tfset