Metadata-Version: 1.1
Name: tfset
Version: 1.2
Summary: Set Tensor values during training in Tensorflow.
Home-page: https://github.com/ondrejba/tfset
Author: Ondrej Biza
Author-email: ondrej.biza@gmail.com
License: MIT
Keywords: tensorflow interactive
Platform: UNKNOWN
Classifier: Development Status :: 5 - Production/Stable
Classifier: Intended Audience :: Science/Research
Classifier: License :: OSI Approved :: MIT License
Classifier: Natural Language :: English
Classifier: Programming Language :: Python :: 3
Classifier: Topic :: Scientific/Engineering :: Artificial Intelligence
